LICENSE
README.md
setup.py
dinamic_py_loader/__init__.py
dinamic_py_loader/dinamic_loader.py
dinamic_py_loader/module_controller.py
dinamic_py_loader/package_controller.py
dinamic_py_loader/tests/__init__.py
dinamic_py_loader/tests/direct_module.py
dinamic_py_loader/tests/unittests.py
dinamic_py_loader/tests/pkg1/__init__.py
dinamic_py_loader/tests/pkg1/source_1.py
dinamic_py_loader/tests/pkg1/pkg1_sub_pkg/__init__.py
dinamic_py_loader/tests/pkg1/pkg1_sub_pkg/source_1_1.py
dinamic_py_loader/tests/коська/__init__.py
dinamic_py_loader/tests/коська/cat_module.py
dinamic_py_loader/tests/коська/подкоська/__init__.py
dinamic_py_loader/tests/коська/подкоська/sub_cat_module.py
dynamic_py_loader.egg-info/PKG-INFO
dynamic_py_loader.egg-info/SOURCES.txt
dynamic_py_loader.egg-info/dependency_links.txt
dynamic_py_loader.egg-info/top_level.txt