Metadata-Version: 2.1
Name: dynamic_py_loader
Version: 1.0.0b2
Summary: A simple dynamic packages and modules loaders.
Home-page: https://github.com/Waffe-Wafle/dynamic_py_loader
Author: Waffe-Wafle
License: MIT
Classifier: Programming Language :: Python :: 3
Classifier: License :: OSI Approved :: MIT License
Classifier: Operating System :: OS Independent
Requires-Python: >=3.6
License-File: LICENSE
